Metadata-Version: 2.0
Name: flask-restplus-patched-aher93
Version: 0.1.10
Summary: Extends Flask-RESTplus so it can handle Marshmallow schemas and Webargs arguments.
Home-page: https://github.com/aher93/flask-restplus-patched
Author: Aden Herold
Author-email: aden.herold1@gmail.com
License: UNKNOWN
Platform: any
Classifier: Development Status :: 2 - Pre-Alpha
Classifier: Environment :: Web Environment
Classifier: Intended Audience :: Developers
Classifier: Operating System :: OS Independent
Classifier: Programming Language :: Python
Classifier: Programming Language :: Python :: 2
Classifier: Programming Language :: Python :: 2.7
Classifier: Programming Language :: Python :: 3
Classifier: Programming Language :: Python :: 3.5
Requires-Dist: Flask
Requires-Dist: flask-restplus
Requires-Dist: marshmallow
Requires-Dist: flask-marshmallow
Requires-Dist: webargs
Requires-Dist: apispec
